mcp_auto_register/__init__.py
mcp_auto_register/register.py
mcp_auto_register-1.0.2.dist-info/METADATA
mcp_auto_register-1.0.2.dist-info/WHEEL
mcp_auto_register-1.0.2.dist-info/RECORD
