Metadata-Version: 2.4
Name: mcp_auto_register
Version: 1.0.2
Summary: Automate registering functions in a python package as MCP tools.
Project-URL: Homepage, https://github.com/JoshuaSiraj/mcp_auto_register
Author-email: Joshua Siraj <joshua.siraj@torontomu.ca>
Classifier: License :: OSI Approved :: MIT License
Classifier: Natural Language :: English
Classifier: Operating System :: OS Independent
Classifier: Programming Language :: Python :: 3.10
Classifier: Programming Language :: Python :: 3.11
Classifier: Programming Language :: Python :: 3.12
Requires-Python: >=3.10
Requires-Dist: mcp[cli]<2,>=1.6.0
